fmscraper/__init__.py
fmscraper/fotmob_stats.py
fmscraper/xmas_generator.py
fmscraper-0.1.4.dist-info/licenses/LICENSE
fmscraper-0.1.4.dist-info/METADATA
fmscraper-0.1.4.dist-info/WHEEL
fmscraper-0.1.4.dist-info/top_level.txt
fmscraper-0.1.4.dist-info/RECORD
