Metadata-Version: 2.4
Name: fmscraper
Version: 0.1.4
Summary: Scraper for FotMob matches
Author: Mieszko Pugowski
License-Expression: MIT
Project-URL: Homepage, https://github.com/MieszkoPugowski/FMScraper
Requires-Python: >=3.8
License-File: LICENSE
Requires-Dist: requests
Dynamic: license-file
